ScheduledTask/__init__.py
ScheduledTask/decorator.py
python_scheduled_task-0.1.2.dist-info/METADATA
python_scheduled_task-0.1.2.dist-info/WHEEL
python_scheduled_task-0.1.2.dist-info/top_level.txt
python_scheduled_task-0.1.2.dist-info/RECORD
