Metadata-Version: 2.1
Name: python-scheduled-task
Version: 0.1.2
Summary: Python Scheduled Task
Home-page: UNKNOWN
Author: Li Shunan
Author-email: lishunan246@gmail.com
License: MIT
Platform: UNKNOWN
Classifier: License :: OSI Approved :: MIT License
Classifier: Programming Language :: Python :: 3
Classifier: Programming Language :: Python :: 3.8
Classifier: Operating System :: POSIX
Requires-Dist: crontab
Requires-Dist: six
